{
    "id": "52",
    "partitionkey": "ConnectorList",
    "alias": "tt.search",
    "info": {
        "title": "Get Search Thought Trace documents",
        "description": "Pull Thougth Trace documents",
        "entityType": "Search",
        "dataSourceId": "47",
        "version": "1.0",
        "subType": "Parent"
    },
    "preRelease": true,
    "request": {
        "endpointPath": "/documents/search",
        "method": "POST",
        "parameters": [
            {
                "cdmName": "ResultSize",
                "name": "top",
                "inClause": "Body",
                "required": true,
                "type": "int",
                "defaultValue": 10
            },
            {
                "cdmName": "Archived.filter",
                "name": "archivedFilter",
                "inClause": "Body",
                "required": false,
                "type": "string",
                "defaultValue": "ExcludeArchived"
            }
        ],
        "sorting": {
            "properties": [
                {
                    "name": "Date",
                    "type": "date",
                    "element": "sort",
                    "elementValue": "CreatedOn"
                },
                {
                    "name": "Alphabetical",
                    "type": "string",
                    "element": "sort",
                    "elementValue": "Name"
                },
                {
                    "name": "Relevance",
                    "type": "string",
                    "element": "sort",
                    "elementValue": "Score"
                }
            ]
        }
    },
    "response": {
        "type": "JSON"
    },
    "filters": [],
    "pagination": {
        "available": true,
        "isZeroBasedOffset": false
    },
    "resultLocation": "",
    "cdmMapping": {
        "structured": [
            {
                "name": "Documents",
                "type": "object",
                "responseElement": "{53}",
                "_comment": ""
            }
        ],
        "unstructured": []
    }
}